odoo8_addon_l10n_it_fatturapa_export_zip-8.0.1.0.0.99.dev8-nspkg.pth
odoo_addons/l10n_it_fatturapa_export_zip/README.rst
odoo_addons/l10n_it_fatturapa_export_zip/__init__.py
odoo_addons/l10n_it_fatturapa_export_zip/__openerp__.py
odoo_addons/l10n_it_fatturapa_export_zip/i18n/l10n_it_fatturapa_export_zip.pot
odoo_addons/l10n_it_fatturapa_export_zip/models/__init__.py
odoo_addons/l10n_it_fatturapa_export_zip/models/attachment.py
odoo_addons/l10n_it_fatturapa_export_zip/readme/CONTRIBUTORS.rst
odoo_addons/l10n_it_fatturapa_export_zip/readme/DESCRIPTION.rst
odoo_addons/l10n_it_fatturapa_export_zip/static/description/icon.png
odoo_addons/l10n_it_fatturapa_export_zip/static/description/index.html
odoo_addons/l10n_it_fatturapa_export_zip/views/attachment_view.xml
odoo_addons/l10n_it_fatturapa_export_zip/wizard/__init__.py
odoo_addons/l10n_it_fatturapa_export_zip/wizard/export_fatturapa.py
odoo_addons/l10n_it_fatturapa_export_zip/wizard/export_fatturapa_view.xml
odoo8_addon_l10n_it_fatturapa_export_zip-8.0.1.0.0.99.dev8.dist-info/METADATA
odoo8_addon_l10n_it_fatturapa_export_zip-8.0.1.0.0.99.dev8.dist-info/WHEEL
odoo8_addon_l10n_it_fatturapa_export_zip-8.0.1.0.0.99.dev8.dist-info/namespace_packages.txt
odoo8_addon_l10n_it_fatturapa_export_zip-8.0.1.0.0.99.dev8.dist-info/top_level.txt
odoo8_addon_l10n_it_fatturapa_export_zip-8.0.1.0.0.99.dev8.dist-info/RECORD
